{"name":"Validate that the web user is able to perform flight bookings","id":"the-newtours-website-is-used-for-flight-bookings.;validate-that-the-web-user-is-able-to-perform-flight-bookings","testSteps":[{"number":1,"description":"Example #1: {Departing From\u003dAcapulco, On Month\u003dNovember, On Day\u003d10, Arriving In\u003dFrankfurt, Returning Month\u003dNovember, Returning Day\u003d17, Airline\u003dBlue Skies Airlines}","duration":45536,"startTime":"2019-01-13T17:42:48.232Z[Europe/London]","result":"SUCCESS","precondition":false,"level":0,"children":[{"number":2,"description":"Given I am a web user who navigates to the NewTours website","duration":1088,"startTime":"2019-01-13T17:42:48.232Z[Europe/London]","result":"SUCCESS","precondition":false,"level":1,"children":[{"number":3,"description":"Launch browser and navigate to test URL","duration":1081,"startTime":"2019-01-13T17:42:48.239Z[Europe/London]","result":"SUCCESS","precondition":false,"level":2,"children":[{"number":4,"description":"Log: the browser is successfully launched.","duration":1,"startTime":"2019-01-13T17:42:49.318Z[Europe/London]","result":"SUCCESS","precondition":false,"level":3}]}]},{"number":5,"description":"When I provide valid username as \"testuser120119\" and password as \"Welcome1!\"","duration":37849,"startTime":"2019-01-13T17:42:49.321Z[Europe/London]","result":"SUCCESS","precondition":false,"level":1,"children":[{"number":6,"description":"Enter registered user details: testuser120119, Welcome1!","duration":37845,"startTime":"2019-01-13T17:42:49.324Z[Europe/London]","result":"SUCCESS","precondition":false,"level":2}]},{"number":7,"description":"Then the user successfully logs in and is able to see the bookings page","duration":51,"startTime":"2019-01-13T17:43:27.170Z[Europe/London]","result":"SUCCESS","precondition":false,"level":1,"children":[{"number":8,"description":"Is flight finder page displayed","duration":50,"startTime":"2019-01-13T17:43:27.171Z[Europe/London]","result":"SUCCESS","precondition":false,"level":2}]},{"number":9,"description":"And provides \"Acapulco\" , \"November\" , \"10\"","duration":608,"startTime":"2019-01-13T17:43:27.221Z[Europe/London]","result":"SUCCESS","precondition":false,"level":1,"children":[{"number":10,"description":"Enter origin location booking details: Acapulco, November, 10","duration":606,"startTime":"2019-01-13T17:43:27.223Z[Europe/London]","result":"SUCCESS","precondition":false,"level":2}]},{"number":11,"description":"And provides \"Frankfurt\" , \"November\" , \"17\" , \"Blue Skies Airlines\"","duration":2427,"startTime":"2019-01-13T17:43:27.830Z[Europe/London]","result":"SUCCESS","precondition":false,"level":1,"children":[{"number":12,"description":"Enter arriving location booking details: Frankfurt, November, 17, Blue Skies Airlines","duration":2425,"startTime":"2019-01-13T17:43:27.832Z[Europe/London]","result":"SUCCESS","precondition":false,"level":2}]},{"number":13,"description":"Then the user is able to successfully make the booking","duration":3508,"startTime":"2019-01-13T17:43:30.259Z[Europe/London]","result":"SUCCESS","precondition":false,"level":1,"children":[{"number":14,"description":"User proceeds with booking","duration":3507,"startTime":"2019-01-13T17:43:30.260Z[Europe/London]","result":"SUCCESS","precondition":false,"level":2,"children":[{"number":15,"description":"Log: The user has successfully made Flight bookings.","duration":1,"startTime":"2019-01-13T17:43:33.762Z[Europe/London]","result":"SUCCESS","precondition":false,"level":3},{"number":16,"description":"Log: view the following screenshot: /src/test/resources/files/screenshots/Booking confirmation_13012019_174332.png","duration":2,"startTime":"2019-01-13T17:43:33.765Z[Europe/London]","result":"SUCCESS","precondition":false,"level":3}]}]}]},{"number":17,"description":"Example #2: {Departing From\u003dLondon, On Month\u003dDecember, On Day\u003d20, Arriving In\u003dNew York, Returning Month\u003dDecember, Returning Day\u003d30, Airline\u003dUnified Airlines}","duration":49290,"startTime":"2019-01-13T17:43:33.774Z[Europe/London]","result":"SUCCESS","precondition":false,"level":0,"children":[{"number":18,"description":"Given I am a web user who navigates to the NewTours website","duration":567,"startTime":"2019-01-13T17:43:33.775Z[Europe/London]","result":"SUCCESS","precondition":false,"level":1,"children":[{"number":19,"description":"Launch browser and navigate to test URL","duration":552,"startTime":"2019-01-13T17:43:33.789Z[Europe/London]","result":"SUCCESS","precondition":false,"level":2,"children":[{"number":20,"description":"Log: the browser is successfully launched.","duration":0,"startTime":"2019-01-13T17:43:34.337Z[Europe/London]","result":"SUCCESS","precondition":false,"level":3}]}]},{"number":21,"description":"When I provide valid username as \"testuser120119\" and password as \"Welcome1!\"","duration":42531,"startTime":"2019-01-13T17:43:34.343Z[Europe/London]","result":"SUCCESS","precondition":false,"level":1,"children":[{"number":22,"description":"Enter registered user details: testuser120119, Welcome1!","duration":42526,"startTime":"2019-01-13T17:43:34.347Z[Europe/London]","result":"SUCCESS","precondition":false,"level":2}]},{"number":23,"description":"Then the user successfully logs in and is able to see the bookings page","duration":72,"startTime":"2019-01-13T17:44:16.874Z[Europe/London]","result":"SUCCESS","precondition":false,"level":1,"children":[{"number":24,"description":"Is flight finder page displayed","duration":70,"startTime":"2019-01-13T17:44:16.875Z[Europe/London]","result":"SUCCESS","precondition":false,"level":2}]},{"number":25,"description":"And provides \"London\" , \"December\" , \"20\"","duration":756,"startTime":"2019-01-13T17:44:16.946Z[Europe/London]","result":"SUCCESS","precondition":false,"level":1,"children":[{"number":26,"description":"Enter origin location booking details: London, December, 20","duration":756,"startTime":"2019-01-13T17:44:16.946Z[Europe/London]","result":"SUCCESS","precondition":false,"level":2}]},{"number":27,"description":"And provides \"New York\" , \"December\" , \"30\" , \"Unified Airlines\"","duration":2698,"startTime":"2019-01-13T17:44:17.703Z[Europe/London]","result":"SUCCESS","precondition":false,"level":1,"children":[{"number":28,"description":"Enter arriving location booking details: New York, December, 30, Unified Airlines","duration":2696,"startTime":"2019-01-13T17:44:17.704Z[Europe/London]","result":"SUCCESS","precondition":false,"level":2}]},{"number":29,"description":"Then the user is able to successfully make the booking","duration":2663,"startTime":"2019-01-13T17:44:20.401Z[Europe/London]","result":"SUCCESS","precondition":false,"level":1,"children":[{"number":30,"description":"User proceeds with booking","duration":2659,"startTime":"2019-01-13T17:44:20.404Z[Europe/London]","result":"SUCCESS","precondition":false,"level":2,"children":[{"number":31,"description":"Log: The user has successfully made Flight bookings.","duration":2,"startTime":"2019-01-13T17:44:23.057Z[Europe/London]","result":"SUCCESS","precondition":false,"level":3},{"number":32,"description":"Log: view the following screenshot: /src/test/resources/files/screenshots/Booking confirmation_13012019_174421.png","duration":2,"startTime":"2019-01-13T17:44:23.061Z[Europe/London]","result":"SUCCESS","precondition":false,"level":3}]}]}]}],"userStory":{"id":"the-newtours-website-is-used-for-flight-bookings.","storyName":"The NewTours website is used for flight bookings.","path":"src/test/resources/features/NewToursTesting.feature","type":"feature"},"featureTag":{"name":"Features/The NewTours website is used for flight bookings.","type":"feature"},"title":"Validate that the web user is able to perform flight bookings","tags":[{"name":"The NewTours website is used for flight bookings.","type":"feature"}],"startTime":"2019-01-13T17:42:48.228Z[Europe/London]","duration":94837,"projectKey":"","dataTable":{"headers":["Departing From","On Month","On Day","Arriving In","Returning Month","Returning Day","Airline"],"rows":[{"values":["Acapulco","November","10","Frankfurt","November","17","Blue Skies Airlines"],"result":"SUCCESS"},{"values":["London","December","20","New York","December","30","Unified Airlines"],"result":"SUCCESS"}],"predefinedRows":true,"scenarioOutline":"Given I am a web user who navigates to the NewTours website\n\rWhen I provide valid username as \"testuser120119\" and password as \"Welcome1!\"\n\rThen the user successfully logs in and is able to see the bookings page\n\rAnd provides \"\u003cDeparting From\u003e\" , \"\u003cOn Month\u003e\" , \"\u003cOn Day\u003e\"\n\rAnd provides \"\u003cArriving In\u003e\" , \"\u003cReturning Month\u003e\" , \"\u003cReturning Day\u003e\" , \"\u003cAirline\u003e\"\n\rThen the user is able to successfully make the booking\n\r","dataSetDescriptors":[{"startRow":0,"rowCount":0,"name":""}]},"manual":false,"testSource":"Cucumber","result":"SUCCESS","scenarioOutline":"Given I am a web user who navigates to the NewTours website\r\nWhen I provide valid username as \"testuser120119\" and password as \"Welcome1!\"\r\nThen the user successfully logs in and is able to see the bookings page\r\nAnd provides \"\u003cDeparting From\u003e\" , \"\u003cOn Month\u003e\" , \"\u003cOn Day\u003e\"\r\nAnd provides \"\u003cArriving In\u003e\" , \"\u003cReturning Month\u003e\" , \"\u003cReturning Day\u003e\" , \"\u003cAirline\u003e\"\r\nThen the user is able to successfully make the booking"}